sleepyr/__init__.py
sleepyr/client.py
sleepyr/exceptions.py
sleepyr-0.0.2.dist-info/LICENSE
sleepyr-0.0.2.dist-info/WHEEL
sleepyr-0.0.2.dist-info/METADATA
sleepyr-0.0.2.dist-info/RECORD
